itsim_scripts/__init__.py
itsim_scripts/i18n.json
itsim_scripts/utils.py
itsim_scripts/bash/simplify_shapefile
itsim_scripts/node_modules/.yarn-integrity
itsim_scripts/node_modules/.bin/mapshaper
itsim_scripts/node_modules/.bin/mapshaper-gui
itsim_scripts/node_modules/.bin/mapshaper-xl
itsim_scripts/node_modules/.bin/mcs2cs
itsim_scripts/node_modules/.bin/mproj
itsim_scripts/node_modules/@types/concat-stream/README.md
itsim_scripts/node_modules/@types/concat-stream/index.d.ts
itsim_scripts/node_modules/@types/concat-stream/package.json
itsim_scripts/node_modules/@types/concat-stream/types-metadata.json
itsim_scripts/node_modules/@types/form-data/README.md
itsim_scripts/node_modules/@types/form-data/index.d.ts
itsim_scripts/node_modules/@types/form-data/package.json
itsim_scripts/node_modules/@types/form-data/types-metadata.json
itsim_scripts/node_modules/@types/node/LICENSE
itsim_scripts/node_modules/@types/node/README.md
itsim_scripts/node_modules/@types/node/assert.d.ts
itsim_scripts/node_modules/@types/node/async_hooks.d.ts
itsim_scripts/node_modules/@types/node/base.d.ts
itsim_scripts/node_modules/@types/node/buffer.d.ts
itsim_scripts/node_modules/@types/node/child_process.d.ts
itsim_scripts/node_modules/@types/node/cluster.d.ts
itsim_scripts/node_modules/@types/node/console.d.ts
itsim_scripts/node_modules/@types/node/constants.d.ts
itsim_scripts/node_modules/@types/node/crypto.d.ts
itsim_scripts/node_modules/@types/node/dgram.d.ts
itsim_scripts/node_modules/@types/node/dns.d.ts
itsim_scripts/node_modules/@types/node/domain.d.ts
itsim_scripts/node_modules/@types/node/events.d.ts
itsim_scripts/node_modules/@types/node/fs.d.ts
itsim_scripts/node_modules/@types/node/globals.d.ts
itsim_scripts/node_modules/@types/node/globals.global.d.ts
itsim_scripts/node_modules/@types/node/http.d.ts
itsim_scripts/node_modules/@types/node/http2.d.ts
itsim_scripts/node_modules/@types/node/https.d.ts
itsim_scripts/node_modules/@types/node/index.d.ts
itsim_scripts-0.5.0.dist-info/LICENSE
itsim_scripts-0.5.0.dist-info/METADATA
itsim_scripts-0.5.0.dist-info/WHEEL
itsim_scripts-0.5.0.dist-info/top_level.txt
itsim_scripts-0.5.0.dist-info/RECORD
